learntools/Learning.py
learntools/Network.py
learntools/VariableStructure.py
learntools/__init__.py
learntools-0.0.20.dist-info/LICENSE
learntools-0.0.20.dist-info/METADATA
learntools-0.0.20.dist-info/WHEEL
learntools-0.0.20.dist-info/top_level.txt
learntools-0.0.20.dist-info/RECORD
